pinard/__init__.py
pinard/utils.py
pinard/augmentation/__init__.py
pinard/augmentation/_random_augmentation.py
pinard/augmentation/_spline_augmentation.py
pinard/augmentation/augmenter.py
pinard/model_selection/__init__.py
pinard/model_selection/_data_driven_sampling.py
pinard/model_selection/_helpers.py
pinard/model_selection/_nirs_sampling.py
pinard/model_selection/_random_sampling.py
pinard/preprocessing/__init__.py
pinard/preprocessing/_nirs.py
pinard/preprocessing/_scaler.py
pinard/preprocessing/_standard.py
pinard/sklearn/__init__.py
pinard/sklearn/_pipeline.py
pinard/sklearn/_utils.py
tests/__init__.py
tests/conftest.py
tests/test_augmentation.py
tests/test_preprocessing.py
tests/test_selection.py
tests/test_sklearn.py
tests/test_utils.py
pinard-1.1.2.dist-info/LICENSE
pinard-1.1.2.dist-info/METADATA
pinard-1.1.2.dist-info/WHEEL
pinard-1.1.2.dist-info/entry_points.txt
pinard-1.1.2.dist-info/top_level.txt
pinard-1.1.2.dist-info/RECORD
